[
  {
    "Name": "Fáraók Kincse 200",
    "Price": 200,
    "ReleaseDate": "2005-04-30",
    "EndDate": "2011-01-28",
    "TotalSupply": 5000000,
    "PrizeStructure": {
      "5000000": 10,
      "50000": 75,
      "20000": 273,
      "10000": 749,
      "5000": 2264,
      "2000": 5800,
      "1000": 61502,
      "500": 355062,
      "200": 1356735
    }
  },
  {
    "Name": "Szerencsesüti",
    "Price": 200,
    "ReleaseDate": "2008-09-12",
    "EndDate": "2010-02-26",
    "TotalSupply": 5000000,
    "PrizeStructure": {
      "5000000": 5,
      "50000": 300,
      "10000": 500,
      "5000": 5000,
      "1000": 50000,
      "400": 850000,
      "200": 700000
    }
  },
  {
    "Name": "Póker",
    "Price": 300,
    "ReleaseDate": "2008-11-07",
    "EndDate": "2011-10-28",
    "TotalSupply": 5000000,
    "PrizeStructure": {
      "10000000": 4,
      "1000000": 5,
      "10000": 1538,
      "5000": 25000,
      "1800": 25000,
      "1000": 50000,
      "800": 150000,
      "500": 550000,
      "300": 600000
    }
  },
  {
    "Name": "Black Jack 200",
    "Price": 200,
    "ReleaseDate": "2008-11-29",
    "EndDate": "2018-06-24",
    "TotalSupply": 5000000,
    "PrizeStructure": {
      "10000000": 4,
      "50000": 40,
      "10000": 800,
      "1000": 150000,
      "500": 400000,
      "200": 1000000
    }
  },
  {
    "Name": "Szuper Bankó",
    "Price": 500,
    "ReleaseDate": "2008-11-29",
    "TotalSupply": 2500000,
    "PrizeStructure": {
      "25000000": 1,
      "5000000": 5,
      "50000": 32,
      "15500": 300,
      "10000": 12500,
      "5000": 25000,
      "3500": 12500,
      "2500": 14500,
      "1500": 17500,
      "1000": 200000,
      "500": 400000
    }
  },
  {
    "Name": "Üveggolyó",
    "Price": 200,
    "ReleaseDate": "2009-03-27",
    "EndDate": "2010-04-25",
    "TotalSupply": 5000000,
    "PrizeStructure": {
      "5000000": 5,
      "50000": 100,
      "2000": 5000,
      "1000": 50000,
      "600": 100000,
      "300": 1500000
    }
  },
  {
    "Name": "Kincskereső",
    "Price": 200,
    "ReleaseDate": "2009-05-29",
    "EndDate": "2010-10-24",
    "TotalSupply": 5000000,
    "PrizeStructure": {
      "5000000": 5,
      "500000": 10,
      "10000": 1000,
      "5000": 10000,
      "1000": 50000,
      "500": 600000,
      "200": 800000
    }
  },
  {
    "Name": "Szerencsekoktél",
    "Price": 300,
    "ReleaseDate": "2009-07-31",
    "EndDate": "2010-09-26",
    "TotalSupply": 5000000,
    "PrizeStructure": {
      "15000000": 3,
      "1000000": 5,
      "100000": 25,
      "10000": 9750,
      "5000": 10000,
      "1800": 50000,
      "1000": 50000,
      "800": 50000,
      "500": 650000,
      "300": 750000
    }
  },
  {
    "Name": "Derby",
    "Price": 200,
    "ReleaseDate": "2009-09-25",
    "EndDate": "2011-07-01",
    "TotalSupply": 5000000,
    "PrizeStructure": {
      "5000000": 5,
      "100000": 50,
      "50000": 500,
      "25000": 1000,
      "5000": 10000,
      "2000": 17500,
      "1000": 50000,
      "500": 100000,
      "300": 650000,
      "200": 700000
    }
  },
  {
    "Name": "Édes Élet",
    "Price": 300,
    "ReleaseDate": "2009-11-27",
    "EndDate": "2012-04-27",
    "TotalSupply": 5000000,
    "PrizeStructure": {
      "15000000": 5,
      "1000000": 10,
      "100000": 350,
      "5000": 25000,
      "1000": 150000,
      "500": 650000,
      "300": 700000
    }
  },
  {
    "Name": "Afrika",
    "Price": 200,
    "ReleaseDate": "2010-01-29",
    "EndDate": "2011-03-25",
    "TotalSupply": 5000000,
    "PrizeStructure": {
      "5000000": 3,
      "1000000": 5,
      "50000": 20,
      "5000": 5800,
      "1000": 50000,
      "500": 400000,
      "300": 1000000
    }
  },
  {
    "Name": "Állatvilág",
    "Price": 200,
    "ReleaseDate": "2010-03-26",
    "EndDate": "2012-04-06",
    "TotalSupply": 5000000,
    "PrizeStructure": {
      "5000000": 4,
      "500000": 5,
      "100000": 25,
      "2000": 50000,
      "500": 650000,
      "200": 750000
    }
  },
  {
    "Name": "Gólparádé",
    "Price": 200,
    "ReleaseDate": "2010-05-21",
    "EndDate": "2013-02-22",
    "TotalSupply": 5000000,
    "PrizeStructure": {
      "5000000": 5,
      "50000": 400,
      "10000": 2000,
      "5000": 25000,
      "1000": 50000,
      "300": 700000,
      "200": 750000
    }
  },
  {
    "Name": "Nyerőkártya",
    "Price": 300,
    "ReleaseDate": "2010-07-30",
    "EndDate": "2013-05-24",
    "TotalSupply": 5000000,
    "PrizeStructure": {
      "15000000": 3,
      "1000000": 6,
      "50000": 500,
      "10000": 2500,
      "6800": 5000,
      "5000": 10000,
      "1800": 50000,
      "1000": 50000,
      "800": 200000,
      "500": 500000,
      "300": 650000
    }
  },
  {
    "Name": "Kockapárbaj",
    "Price": 300,
    "ReleaseDate": "2010-09-24",
    "EndDate": "2012-07-27",
    "TotalSupply": 5000000,
    "PrizeStructure": {
      "10000000": 3,
      "100000": 500,
      "5000": 10000,
      "1800": 50000,
      "1000": 50000,
      "800": 250000,
      "500": 500000,
      "300": 700000
    }
  },
  {
    "Name": "Gyémánt",
    "Price": 300,
    "ReleaseDate": "2010-11-26",
    "EndDate": "2012-01-27",
    "TotalSupply": 5000000,
    "PrizeStructure": {
      "15000000": 5,
      "1000000": 10,
      "100000": 200,
      "5000": 10000,
      "3000": 25000,
      "1500": 50000,
      "1000": 50000,
      "600": 300000,
      "500": 400000,
      "300": 650000
    }
  },
  {
    "Name": "Fáraók Kincse 300",
    "Price": 300,
    "ReleaseDate": "2011-01-14",
    "TotalSupply": 5000000,
    "PrizeStructure": {
      "5000500": 3,
      "5000000": 10,
      "60000": 25,
      "50300": 25,
      "50000": 25,
      "30000": 50,
      "25000": 50,
      "21000": 52,
      "20500": 60,
      "20000": 61,
      "15000": 64,
      "10300": 110,
      "10000": 2001,
      "7000": 1000,
      "6000": 1001,
      "5000": 15000,
      "3000": 2000,
      "2500": 1000,
      "2000": 4000,
      "1500": 4000,
      "1300": 9300,
      "1000": 50000,
      "800": 250000,
      "500": 350000,
      "300": 950000
    }
  },
  {
    "Name": "Világutazó",
    "Price": 200,
    "ReleaseDate": "2011-03-11",
    "EndDate": "2012-07-27",
    "TotalSupply": 5000000,
    "PrizeStructure": {
      "5000000": 3,
      "1000000": 5,
      "50000": 20,
      "5000": 5800,
      "1000": 50000,
      "500": 400000,
      "300": 1000000
    }
  },
  {
    "Name": "Buksza 66",
    "Price": 1000,
    "ReleaseDate": "2011-05-06",
    "TotalSupply": 2500000,
    "PrizeStructure": {
      "50000000": 1,
      "5000000": 3,
      "100000": 50,
      "50000": 150,
      "27000": 500,
      "22000": 1000,
      "11000": 2000,
      "10000": 10000,
      "9000": 5000,
      "8000": 5000,
      "6000": 5000,
      "5000": 25000,
      "4000": 50000,
      "3000": 50000,
      "2000": 250000,
      "1000": 350000
    }
  },
  {
    "Name": "Szerencsepatkó",
    "Price": 200,
    "ReleaseDate": "2011-06-24",
    "EndDate": "2012-06-15",
    "TotalSupply": 5000000,
    "PrizeStructure": {
      "5000000": 5,
      "1000000": 10,
      "100000": 50,
      "50000": 100,
      "10000": 500,
      "5000": 8000,
      "1000": 100000,
      "500": 150000,
      "300": 650000,
      "200": 700000
    }
  },
  {
    "Name": "Áll az alku",
    "Price": 300,
    "ReleaseDate": "2011-08-26",
    "EndDate": "2012-08-31",
    "TotalSupply": 5000000,
    "PrizeStructure": {
      "15000000": 3,
      "1000000": 10,
      "50000": 50,
      "20000": 75,
      "10000": 100,
      "3000": 50000,
      "1500": 50000,
      "1000": 100000,
      "600": 150000,
      "500": 200000,
      "400": 400000,
      "300": 650000
    }
  },
  {
    "Name": "Boldog karácsonyt! 2011",
    "Price": 500,
    "ReleaseDate": "2011-10-28",
    "EndDate": "2012-01-06",
    "TotalSupply": 1500000,
    "PrizeStructure": {
      "25000000": 1,
      "5000000": 3,
      "50000": 126,
      "15500": 400,
      "10000": 4000,
      "5000": 10000,
      "1500": 60000,
      "1000": 150000,
      "500": 210000
    }
  },
  {
    "Name": "Karátok közt",
    "Price": 500,
    "ReleaseDate": "2012-01-27",
    "EndDate": "2014-05-23",
    "TotalSupply": 5000000,
    "PrizeStructure": {
      "25000000": 2,
      "5000000": 5,
      "100000": 21,
      "15000": 860,
      "6000": 10000,
      "4000": 50000,
      "2500": 50000,
      "2000": 100000,
      "1500": 100000,
      "1000": 500000,
      "500": 600000
    }
  },
  {
    "Name": "Állati Sztárok",
    "Price": 200,
    "ReleaseDate": "2012-03-30",
    "EndDate": "2013-02-22",
    "TotalSupply": 5000000,
    "PrizeStructure": {
      "5000000": 3,
      "500000": 5,
      "50000": 50,
      "5000": 6000,
      "1000": 50000,
      "500": 400000,
      "300": 1000000
    }
  },
  {
    "Name": "Nasi",
    "Price": 200,
    "ReleaseDate": "2012-05-25",
    "EndDate": "2013-10-18",
    "TotalSupply": 5000000,
    "PrizeStructure": {
      "5000000": 3,
      "500000": 50,
      "50000": 200,
      "5000": 10000,
      "1000": 50000,
      "400": 800000,
      "200": 650000
    }
  },
  {
    "Name": "Tengeri Kincsek",
    "Price": 300,
    "ReleaseDate": "2012-08-31",
    "EndDate": "2014-01-31",
    "TotalSupply": 5000000,
    "PrizeStructure": {
      "10000000": 3,
      "1000000": 5,
      "500000": 27,
      "100000": 50,
      "50000": 500,
      "6500": 1000,
      "5000": 5000,
      "2000": 10000,
      "1500": 100000,
      "1000": 150000,
      "800": 50000,
      "500": 500000,
      "300": 700000
    }
  },
  {
    "Name": "Boldog karácsonyt! 2012",
    "Price": 500,
    "ReleaseDate": "2012-11-02",
    "EndDate": "2013-01-11",
    "TotalSupply": 1500000,
    "PrizeStructure": {
      "25000000": 1,
      "5000000": 3,
      "50000": 122,
      "16000": 400,
      "10000": 4000,
      "5000": 10000,
      "1500": 60000,
      "1000": 150000,
      "500": 210000
    }
  },
  {
    "Name": "Kávészünet 200",
    "Price": 200,
    "ReleaseDate": "2013-02-01",
    "EndDate": "2014-10-10",
    "TotalSupply": 5000000,
    "PrizeStructure": {
      "5000000": 3,
      "2500000": 6,
      "100000": 50,
      "50000": 200,
      "10000": 2000,
      "5000": 3000,
      "1000": 50000,
      "500": 100000,
      "400": 700000,
      "200": 700000
    }
  },
  {
    "Name": "Monopoly",
    "Price": 300,
    "ReleaseDate": "2013-03-29",
    "EndDate": "2014-07-25",
    "TotalSupply": 5000000,
    "PrizeStructure": {
      "10000000": 3,
      "1000000": 5,
      "100000": 65,
      "19000": 1500,
      "10000": 1500,
      "8000": 2500,
      "7000": 2500,
      "6000": 5000,
      "5000": 5000,
      "4500": 5000,
      "2000": 50000,
      "1000": 50000,
      "600": 50000,
      "500": 650000,
      "300": 750000
    }
  },
  {
    "Name": "Állati Párok",
    "Price": 200,
    "ReleaseDate": "2013-05-31",
    "EndDate": "2014-10-10",
    "TotalSupply": 5000000,
    "PrizeStructure": {
      "5000000": 3,
      "1000000": 5,
      "50000": 40,
      "5000": 3600,
      "1000": 50000,
      "500": 450000,
      "300": 950000
    }
  },
  {
    "Name": "Astro+TV",
    "Price": 300,
    "ReleaseDate": "2013-08-02",
    "EndDate": "2013-08-02",
    "TotalSupply": 5000000,
    "PrizeStructure": {
      "10000000": 3,
      "1000000": 5,
      "10000": 5000,
      "5000": 17000,
      "1500": 30000,
      "1000": 100000,
      "800": 50000,
      "500": 650000,
      "300": 700000
    }
  },
  {
    "Name": "Édenkert",
    "Price": 500,
    "ReleaseDate": "2013-09-27",
    "EndDate": "2015-02-13",
    "TotalSupply": 5000000,
    "PrizeStructure": {
      "24000000": 4,
      "5000000": 5,
      "50000": 270,
      "15500": 1000,
      "10000": 5000,
      "5000": 50000,
      "3000": 50000,
      "2500": 50000,
      "1500": 50000,
      "1000": 500000,
      "500": 650000
    }
  },
  {
    "Name": "Boldog karácsonyt! 2013",
    "Price": 1000,
    "ReleaseDate": "2013-11-06",
    "EndDate": "2014-01-10",
    "TotalSupply": 2000000,
    "PrizeStructure": {
      "50000000": 1,
      "5000000": 2,
      "100000": 20,
      "50000": 30,
      "20000": 1000,
      "11000": 1500,
      "10000": 7000,
      "8000": 7000,
      "6000": 9000,
      "5000": 20000,
      "4000": 40000,
      "3000": 40000,
      "2000": 200000,
      "1000": 280000
    }
  },
  {
    "Name": "Kabala",
    "Price": 200,
    "ReleaseDate": "2014-01-31",
    "EndDate": "2015-03-27",
    "TotalSupply": 6000000,
    "PrizeStructure": {
      "5000000": 3,
      "500000": 3,
      "50000": 50,
      "10000": 200,
      "5000": 3000,
      "1000": 60000,
      "500": 420000,
      "300": 1380000
    }
  },
  {
    "Name": "Nyerő négyes",
    "Price": 500,
    "ReleaseDate": "2014-03-28",
    "EndDate": "2015-09-25",
    "TotalSupply": 5000000,
    "PrizeStructure": {
      "25000000": 4,
      "5000000": 6,
      "50000": 200,
      "15500": 600,
      "5000": 70000,
      "3000": 25000,
      "2500": 65000,
      "1500": 58800,
      "1000": 400000,
      "500": 800000
    }
  },
  {
    "Name": "Rubik kocka",
    "Price": 300,
    "ReleaseDate": "2014-05-30",
    "EndDate": "2016-04-25",
    "TotalSupply": 6000000,
    "PrizeStructure": {
      "10000000": 2,
      "1000000": 4,
      "200000": 5,
      "100000": 15,
      "50000": 310,
      "20000": 1200,
      "10000": 3000,
      "5000": 6000,
      "2000": 60000,
      "1000": 300000,
      "500": 600000,
      "300": 900000
    }
  },
  {
    "Name": "Balaton",
    "Price": 200,
    "ReleaseDate": "2014-07-18",
    "EndDate": "2015-02-13",
    "TotalSupply": 6000000,
    "PrizeStructure": {
      "10000000": 2,
      "1000000": 5,
      "50000": 50,
      "10000": 200,
      "5000": 3700,
      "1000": 60000,
      "500": 360000,
      "300": 1440000
    }
  },
  {
    "Name": "Szuper Black Jack",
    "Price": 500,
    "ReleaseDate": "2014-09-26",
    "TotalSupply": 6000000,
    "PrizeStructure": {
      "25000000": 2,
      "5000000": 8,
      "50000": 200,
      "20000": 2000,
      "10000": 10000,
      "5000": 40000,
      "4000": 20000,
      "2500": 20000,
      "2000": 60000,
      "1000": 840000,
      "500": 840000
    }
  },
  {
    "Name": "Boldog karácsonyt! 2014",
    "Price": 2000,
    "ReleaseDate": "2014-11-07",
    "EndDate": "2015-02-02",
    "TotalSupply": 2000000,
    "PrizeStructure": {
      "75000000": 1,
      "10000000": 10,
      "200000": 100,
      "100000": 125,
      "50000": 1000,
      "25000": 1500,
      "20000": 7000,
      "15000": 7000,
      "12000": 10000,
      "10000": 30000,
      "7000": 40000,
      "5000": 80000,
      "3000": 200000,
      "2000": 240000
    }
  },
  {
    "Name": "Sok szeretettel! 200",
    "Price": 200,
    "ReleaseDate": "2015-01-30",
    "EndDate": "2017-05-27",
    "TotalSupply": 4000000,
    "PrizeStructure": {
      "5000000": 2,
      "100000": 10,
      "50000": 20,
      "10000": 100,
      "5000": 3000,
      "1000": 40000,
      "500": 320000,
      "300": 840000
    }
  },
  {
    "Name": "Bakancslista",
    "Price": 1000,
    "ReleaseDate": "2015-03-27",
    "EndDate": "2018-04-08",
    "TotalSupply": 3000000,
    "PrizeStructure": {
      "48000000": 2,
      "1000000": 10,
      "100000": 100,
      "50000": 110,
      "27000": 500,
      "22000": 2000,
      "10000": 10000,
      "9000": 7000,
      "8000": 6000,
      "6000": 5000,
      "5000": 30000,
      "4000": 60000,
      "3000": 60000,
      "2000": 300000,
      "1000": 420000
    }
  },
  {
    "Name": "Pörgettyű",
    "Price": 300,
    "ReleaseDate": "2015-05-29",
    "EndDate": "2017-05-27",
    "TotalSupply": 4000000,
    "PrizeStructure": {
      "10000000": 2,
      "500000": 4,
      "100000": 10,
      "50000": 50,
      "30000": 200,
      "10000": 600,
      "5000": 1014,
      "2700": 10900,
      "1800": 60000,
      "900": 200000,
      "600": 360000,
      "300": 560000
    }
  },
  {
    "Name": "Szerencsepart",
    "Price": 500,
    "ReleaseDate": "2015-07-17",
    "EndDate": "2016-06-13",
    "TotalSupply": 3000000,
    "PrizeStructure": {
      "25000000": 1,
      "4000000": 3,
      "1000000": 4,
      "500000": 50,
      "100000": 150,
      "10000": 3000,
      "5000": 16000,
      "4000": 10000,
      "3000": 18000,
      "2000": 60000,
      "1000": 360000,
      "500": 420000
    }
  },
  {
    "Name": "Házi kedvenc",
    "Price": 200,
    "ReleaseDate": "2015-09-25",
    "EndDate": "2016-10-24",
    "TotalSupply": 4000000,
    "PrizeStructure": {
      "5000000": 3,
      "100000": 15,
      "20000": 100,
      "10000": 400,
      "5000": 3500,
      "2000": 10000,
      "1000": 40000,
      "500": 280000,
      "300": 800000
    }
  },
  {
    "Name": "Boldog karácsonyt! 2015",
    "Price": 2000,
    "ReleaseDate": "2015-11-06",
    "EndDate": "2016-01-25",
    "TotalSupply": 1800000,
    "PrizeStructure": {
      "75000000": 1,
      "10000000": 3,
      "1000000": 30,
      "100000": 360,
      "40000": 900,
      "30000": 2000,
      "20000": 6000,
      "15000": 7000,
      "10000": 30000,
      "7000": 36000,
      "5000": 72000,
      "3000": 216000,
      "2000": 216000
    }
  },
  {
    "Name": "Pénzfa",
    "Price": 200,
    "ReleaseDate": "2016-01-29",
    "EndDate": "2017-03-27",
    "TotalSupply": 4000000,
    "PrizeStructure": {
      "5000000": 2,
      "500000": 5,
      "10000": 50,
      "5000": 3000,
      "4000": 3000,
      "2000": 4000,
      "1000": 40000,
      "500": 280000,
      "300": 840000
    }
  },
  {
    "Name": "Hurrá 25!",
    "Price": 300,
    "ReleaseDate": "2016-04-01",
    "EndDate": "2016-10-24",
    "TotalSupply": 4000000,
    "PrizeStructure": {
      "25000000": 2,
      "1000000": 5,
      "125000": 150,
      "50000": 145,
      "25000": 300,
      "10000": 1200,
      "7500": 3000,
      "5000": 25000,
      "1000": 120000,
      "400": 520000,
      "300": 560000
    }
  },
  {
    "Name": "Zseton",
    "Price": 500,
    "ReleaseDate": "2016-06-03",
    "EndDate": "2018-04-08",
    "TotalSupply": 3000000,
    "PrizeStructure": {
      "25000000": 1,
      "1000000": 10,
      "100000": 25,
      "25000": 440,
      "20000": 1500,
      "16000": 5000,
      "10000": 2500,
      "6000": 10000,
      "5000": 8000,
      "4500": 3000,
      "2000": 60000,
      "1000": 60000,
      "800": 360000,
      "500": 420000
    }
  },
  {
    "Name": "Kéményseprő",
    "Price": 200,
    "ReleaseDate": "2016-07-29",
    "EndDate": "2017-07-29",
    "TotalSupply": 4000000,
    "PrizeStructure": {
      "5000000": 3,
      "500000": 35,
      "50000": 100,
      "10000": 300,
      "5000": 2700,
      "2000": 15000,
      "1000": 40000,
      "400": 200000,
      "300": 920000
    }
  },
  {
    "Name": "Szerencsenaptár",
    "Price": 1000,
    "ReleaseDate": "2016-09-23",
    "EndDate": "2019-03-31",
    "TotalSupply": 3000000,
    "PrizeStructure": {
      "50000000": 2,
      "1000000": 7,
      "100000": 110,
      "50000": 200,
      "30000": 200,
      "20000": 2000,
      "10000": 6500,
      "9000": 5000,
      "8000": 5000,
      "7000": 5000,
      "6000": 6000,
      "5000": 35000,
      "4000": 60000,
      "3000": 60000,
      "2000": 300000,
      "1000": 420000
    }
  },
  {
    "Name": "Boldog karácsonyt! 2016",
    "Price": 2000,
    "ReleaseDate": "2016-11-04",
    "EndDate": "2017-01-30",
    "TotalSupply": 2300000,
    "PrizeStructure": {
      "75000000": 1,
      "10000000": 15,
      "1000000": 32,
      "100000": 350,
      "50000": 400,
      "40000": 3000,
      "30000": 5000,
      "20000": 7500,
      "15000": 10000,
      "10000": 20000,
      "7000": 30000,
      "6000": 30000,
      "5000": 46000,
      "4000": 46000,
      "3000": 184000,
      "2000": 368000
    }
  },
  {
    "Name": "Labirintus",
    "Price": 300,
    "ReleaseDate": "2017-02-03",
    "EndDate": "2018-04-08",
    "TotalSupply": 4000000,
    "PrizeStructure": {
      "10000000": 2,
      "1000000": 15,
      "100000": 5,
      "50000": 50,
      "20000": 150,
      "10000": 100,
      "5000": 400,
      "2000": 80000,
      "800": 240000,
      "500": 360000,
      "300": 560000
    }
  },
  {
    "Name": "Mega Bankó",
    "Price": 1000,
    "ReleaseDate": "2017-03-31",
    "EndDate": "2019-05-26",
    "TotalSupply": 3000000,
    "PrizeStructure": {
      "50000000": 1,
      "1000000": 10,
      "100000": 80,
      "35000": 300,
      "14000": 1000,
      "10000": 2000,
      "8000": 2500,
      "7000": 2500,
      "6000": 10000,
      "5000": 60000,
      "4000": 60000,
      "3000": 120000,
      "2000": 240000,
      "1000": 420000
    }
  },
  {
    "Name": "Fesztivál",
    "Price": 300,
    "ReleaseDate": "2017-06-02",
    "EndDate": "2017-09-25",
    "TotalSupply": 5000000,
    "PrizeStructure": {
      "10000000": 1,
      "500000": 5,
      "50000": 45,
      "25000": 34,
      "10000": 40,
      "6000": 9000,
      "5000": 18000,
      "1000": 200000,
      "800": 250000,
      "400": 400000,
      "300": 700000
    }
  },
  {
    "Name": "Hoppá! 10x",
    "Price": 300,
    "ReleaseDate": "2017-06-30",
    "EndDate": "2018-08-26",
    "TotalSupply": 5000000,
    "PrizeStructure": {
      "10000000": 1,
      "1000000": 2,
      "100000": 20,
      "51000": 50,
      "23000": 100,
      "11000": 1000,
      "6000": 5025,
      "3000": 50000,
      "1000": 300000,
      "600": 350000,
      "300": 700000
    }
  },
  {
    "Name": "Hoppá! 20x",
    "Price": 500,
    "ReleaseDate": "2017-06-30",
    "EndDate": "2018-08-26",
    "TotalSupply": 4000000,
    "PrizeStructure": {
      "20000000": 2,
      "1000000": 6,
      "100000": 50,
      "50000": 100,
      "30000": 400,
      "20000": 2000,
      "16000": 4000,
      "10000": 5700,
      "6000": 10000,
      "5000": 6000,
      "3500": 6000,
      "2000": 80000,
      "1000": 240000,
      "800": 400000,
      "500": 480000
    }
  },
  {
    "Name": "Hoppá! 50x",
    "Price": 1000,
    "ReleaseDate": "2017-06-30",
    "EndDate": "2018-08-26",
    "TotalSupply": 3000000,
    "PrizeStructure": {
      "50000000": 1,
      "1000000": 6,
      "100000": 115,
      "50000": 300,
      "30000": 350,
      "20000": 2000,
      "10000": 4000,
      "9000": 5000,
      "8000": 7000,
      "7000": 8000,
      "6000": 15000,
      "5000": 30000,
      "4000": 60000,
      "3000": 60000,
      "2000": 300000,
      "1000": 420000
    }
  },
  {
    "Name": "Lottóláz",
    "Price": 500,
    "ReleaseDate": "2017-09-01",
    "EndDate": "2020-06-28",
    "TotalSupply": 3000000,
    "PrizeStructure": {
      "25000000": 1,
      "1000000": 5,
      "600000": 8,
      "200000": 10,
      "50000": 46,
      "40000": 50,
      "30000": 280,
      "22500": 800,
      "20000": 1400,
      "13000": 2500,
      "10000": 3100,
      "3500": 36000,
      "2000": 60000,
      "1000": 300000,
      "500": 540000
    }
  },
  {
    "Name": "Kiskarácsony 2017",
    "Price": 200,
    "ReleaseDate": "2017-11-03",
    "EndDate": "2018-02-04",
    "TotalSupply": 3000000,
    "PrizeStructure": {
      "5000000": 1,
      "100000": 10,
      "50000": 20,
      "10000": 100,
      "5000": 1800,
      "1600": 10000,
      "800": 30000,
      "500": 210000,
      "300": 660000
    }
  },
  {
    "Name": "Nagykarácsony 2017",
    "Price": 2000,
    "ReleaseDate": "2017-11-03",
    "EndDate": "2018-02-04",
    "TotalSupply": 3000000,
    "PrizeStructure": {
      "75000000": 1,
      "10000000": 5,
      "1000000": 55,
      "100000": 650,
      "40000": 1500,
      "30000": 3500,
      "20000": 10000,
      "15000": 10000,
      "10000": 56000,
      "7000": 60000,
      "5000": 120000,
      "3000": 360000,
      "2000": 360000
    }
  },
  {
    "Name": "Black Jack 300",
    "Price": 300,
    "ReleaseDate": "2018-01-05",
    "TotalSupply": 5000000,
    "PrizeStructure": {
      "15000000": 4,
      "100000": 40,
      "50000": 320,
      "10000": 10000,
      "1000": 250000,
      "500": 400000,
      "300": 1000000
    }
  },
  {
    "Name": "Szerencsemalac",
    "Price": 300,
    "ReleaseDate": "2018-01-12",
    "EndDate": "2020-06-28",
    "TotalSupply": 6000000,
    "PrizeStructure": {
      "10000000": 3,
      "500000": 6,
      "10000": 300,
      "5000": 2400,
      "4000": 15000,
      "2000": 60000,
      "1000": 300000,
      "500": 600000,
      "300": 960000
    }
  },
  {
    "Name": "Astro",
    "Price": 300,
    "ReleaseDate": "2018-02-02",
    "TotalSupply": 5000000,
    "PrizeStructure": {
      "10000000": 3,
      "1000000": 5,
      "10000": 6000,
      "5000": 20000,
      "1500": 30000,
      "1000": 100000,
      "800": 50000,
      "500": 650000,
      "300": 750000
    }
  },
  {
    "Name": "Kaszinó 112",
    "Price": 2000,
    "ReleaseDate": "2018-04-06",
    "TotalSupply": 3000000,
    "PrizeStructure": {
      "75000000": 1,
      "10000000": 8,
      "1000000": 25,
      "100000": 1000,
      "50000": 3000,
      "40000": 5000,
      "30000": 7000,
      "20000": 10500,
      "15000": 14000,
      "10000": 16000,
      "7000": 20000,
      "6000": 20000,
      "5000": 60000,
      "4000": 120000,
      "3000": 240000,
      "2000": 480000
    }
  },
  {
    "Name": "Kleopátra kincse",
    "Price": 500,
    "ReleaseDate": "2018-06-01",
    "EndDate": "2020-08-30",
    "TotalSupply": 6000000,
    "PrizeStructure": {
      "25000000": 1,
      "5000000": 5,
      "500000": 40,
      "100000": 60,
      "50000": 100,
      "25000": 168,
      "20000": 650,
      "15000": 500,
      "10000": 2330,
      "7000": 3000,
      "6000": 6000,
      "5000": 24000,
      "2000": 120000,
      "1800": 120000,
      "1000": 480000,
      "800": 360000,
      "500": 840000
    }
  },
  {
    "Name": "Sok szeretettel 300",
    "Price": 300,
    "ReleaseDate": "2018-07-13",
    "EndDate": "2020-06-28",
    "TotalSupply": 6000000,
    "PrizeStructure": {
      "10000000": 2,
      "1000000": 3,
      "100000": 100,
      "50000": 200,
      "10000": 1300,
      "5000": 20000,
      "1000": 240000,
      "600": 720000,
      "300": 960000
    }
  },
  {
    "Name": "Kódfejtő",
    "Price": 1000,
    "ReleaseDate": "2018-09-07",
    "EndDate": "2020-03-15",
    "TotalSupply": 3000000,
    "PrizeStructure": {
      "50000000": 1,
      "5000000": 3,
      "100000": 50,
      "50000": 100,
      "26000": 500,
      "23000": 1000,
      "12000": 2000,
      "10000": 8000,
      "9000": 5000,
      "7000": 5000,
      "6000": 10000,
      "5000": 31000,
      "4000": 60000,
      "3000": 120000,
      "2000": 240000,
      "1000": 420000
    }
  },
  {
    "Name": "Kiskarácsony 2018",
    "Price": 300,
    "ReleaseDate": "2018-11-03",
    "EndDate": "2019-02-03",
    "TotalSupply": 2500000,
    "PrizeStructure": {
      "10000000": 1,
      "1000000": 10,
      "100000": 100,
      "10000": 1500,
      "5000": 3000,
      "3000": 20000,
      "1000": 50000,
      "500": 350000,
      "300": 400000
    }
  },
  {
    "Name": "Nagykarácsony 2018",
    "Price": 3000,
    "ReleaseDate": "2018-11-03",
    "EndDate": "2019-02-03",
    "TotalSupply": 2300000,
    "PrizeStructure": {
      "100000000": 1,
      "10000000": 30,
      "1000000": 100,
      "100000": 1200,
      "40000": 4000,
      "30000": 4000,
      "20000": 6000,
      "15000": 7600,
      "12000": 9000,
      "9000": 92000,
      "6000": 276000,
      "3000": 368000
    }
  },
  {
    "Name": "Bronz",
    "Price": 300,
    "ReleaseDate": "2019-02-08",
    "EndDate": "2020-07-26",
    "TotalSupply": 5000000,
    "PrizeStructure": {
      "10000000": 1,
      "1000000": 5,
      "100000": 30,
      "40000": 45,
      "20000": 100,
      "10000": 1000,
      "6000": 2200,
      "3000": 50000,
      "1000": 150000,
      "600": 600000,
      "300": 750000
    }
  },
  {
    "Name": "Ezüst",
    "Price": 500,
    "ReleaseDate": "2019-02-08",
    "EndDate": "2020-03-15",
    "TotalSupply": 4000000,
    "PrizeStructure": {
      "20000000": 2,
      "1000000": 5,
      "100000": 38,
      "50000": 60,
      "30000": 280,
      "20000": 2000,
      "16000": 1800,
      "10000": 4000,
      "6000": 10000,
      "5000": 6000,
      "3500": 30000,
      "2000": 80000,
      "1000": 240000,
      "800": 320000,
      "500": 560000
    }
  },
  {
    "Name": "Arany",
    "Price": 1000,
    "ReleaseDate": "2019-02-08",
    "EndDate": "2020-03-15",
    "TotalSupply": 3000000,
    "PrizeStructure": {
      "50000000": 1,
      "1000000": 6,
      "100000": 115,
      "50000": 300,
      "30000": 350,
      "20000": 1500,
      "10000": 3050,
      "9000": 5000,
      "8000": 6000,
      "7000": 5500,
      "6000": 12500,
      "5000": 30000,
      "4000": 60000,
      "3000": 60000,
      "2000": 300000,
      "1000": 480000
    }
  },
  {
    "Name": "Pénzlift",
    "Price": 500,
    "ReleaseDate": "2019-03-29",
    "EndDate": "2022-04-24",
    "TotalSupply": 3000000,
    "PrizeStructure": {
      "25000000": 1,
      "1000000": 10,
      "100000": 25,
      "25000": 440,
      "20000": 1500,
      "16000": 5000,
      "10000": 2500,
      "6000": 10000,
      "5000": 8000,
      "4500": 3000,
      "2000": 60000,
      "1000": 60000,
      "800": 360000,
      "500": 420000
    }
  },
  {
    "Name": "Világjáró",
    "Price": 2000,
    "ReleaseDate": "2019-05-10",
    "EndDate": "2020-07-26",
    "TotalSupply": 3000000,
    "PrizeStructure": {
      "75000000": 1,
      "10000000": 10,
      "1000000": 60,
      "100000": 1180,
      "50000": 3000,
      "40000": 5000,
      "30000": 7000,
      "20000": 10000,
      "15000": 10000,
      "10000": 20000,
      "7000": 30000,
      "6000": 36000,
      "5000": 30200,
      "4000": 60000,
      "3000": 300000,
      "2000": 480000
    }
  },
  {
    "Name": "Szerencsehozó",
    "Price": 300,
    "ReleaseDate": "2019-07-12",
    "EndDate": "2020-07-26",
    "TotalSupply": 6000000,
    "PrizeStructure": {
      "10000000": 2,
      "500000": 8,
      "100000": 200,
      "10000": 2000,
      "8000": 4000,
      "5000": 6000,
      "3000": 8000,
      "2000": 60000,
      "1000": 180000,
      "600": 660000,
      "300": 900000
    }
  },
  {
    "Name": "Aranybánya",
    "Price": 1000,
    "ReleaseDate": "2019-09-06",
    "EndDate": "2023-04-23",
    "TotalSupply": 3000000,
    "PrizeStructure": {
      "50000000": 1,
      "1000000": 6,
      "100000": 100,
      "50000": 110,
      "27000": 500,
      "22000": 2000,
      "10000": 5000,
      "9000": 7000,
      "8000": 7250,
      "6000": 20000,
      "5000": 30000,
      "4000": 60000,
      "3000": 60000,
      "2000": 300000,
      "1000": 420000
    }
  },
  {
    "Name": "Kiskarácsony 2019",
    "Price": 300,
    "ReleaseDate": "2019-11-04",
    "EndDate": "2020-02-23",
    "TotalSupply": 2500000,
    "PrizeStructure": {
      "10000000": 1,
      "1000000": 10,
      "100000": 100,
      "10000": 1500,
      "5000": 3000,
      "3000": 20000,
      "1000": 50000,
      "500": 350000,
      "300": 400000
    }
  },
  {
    "Name": "Nagykarácsony 2019",
    "Price": 3000,
    "ReleaseDate": "2019-11-04",
    "EndDate": "2020-02-23",
    "TotalSupply": 2300000,
    "PrizeStructure": {
      "100000000": 1,
      "10000000": 30,
      "1000000": 100,
      "100000": 1200,
      "40000": 4000,
      "30000": 4000,
      "20000": 6000,
      "15000": 7600,
      "12000": 9000,
      "9000": 92000,
      "6000": 276000,
      "3000": 368000
    }
  },
  {
    "Name": "Szerencse vagy Mázli",
    "Price": 500,
    "ReleaseDate": "2020-01-11",
    "EndDate": "2022-04-24",
    "TotalSupply": 3000000,
    "PrizeStructure": {
      "25000000": 1,
      "1000000": 10,
      "100000": 45,
      "50000": 650,
      "30000": 2000,
      "20000": 4500,
      "5000": 9000,
      "1500": 120000,
      "800": 360000,
      "500": 480000
    }
  },
  {
    "Name": "Kis Ajándék",
    "Price": 500,
    "ReleaseDate": "2020-03-20",
    "EndDate": "2022-01-16",
    "TotalSupply": 5000000,
    "PrizeStructure": {
      "20000000": 1,
      "1000000": 3,
      "100000": 23,
      "50000": 60,
      "30000": 170,
      "20000": 1200,
      "16000": 1600,
      "10000": 3000,
      "6000": 7000,
      "5000": 10000,
      "3500": 100000,
      "2000": 100000,
      "1000": 200000,
      "800": 400000,
      "500": 700000
    }
  },
  {
    "Name": "Nagy Ajándék",
    "Price": 1000,
    "ReleaseDate": "2020-03-20",
    "EndDate": "2023-05-21",
    "TotalSupply": 4000000,
    "PrizeStructure": {
      "50000000": 1,
      "1000000": 5,
      "100000": 70,
      "50000": 200,
      "30000": 300,
      "20000": 1000,
      "12000": 1000,
      "10000": 3500,
      "9000": 5500,
      "8000": 6500,
      "7000": 5500,
      "6000": 12000,
      "5000": 47000,
      "4000": 80000,
      "3000": 80000,
      "2000": 480000,
      "1000": 565000
    }
  },
  {
    "Name": "Óriási Ajándék",
    "Price": 2000,
    "ReleaseDate": "2020-03-20",
    "EndDate": "2023-05-21",
    "TotalSupply": 3000000,
    "PrizeStructure": {
      "75000000": 1,
      "10000000": 5,
      "1000000": 25,
      "100000": 200,
      "90000": 300,
      "60000": 1500,
      "51000": 2000,
      "40000": 3500,
      "30000": 4200,
      "27000": 4500,
      "20000": 5000,
      "18000": 6000,
      "17000": 5000,
      "15000": 10000,
      "10000": 10050,
      "9000": 12000,
      "7000": 20000,
      "6000": 15000,
      "5000": 60000,
      "4000": 120000,
      "3000": 240000,
      "2000": 491000
    }
  },
  {
    "Name": "Pénzes bőrönd",
    "Price": 1000,
    "ReleaseDate": "2020-05-08",
    "EndDate": "2023-02-19",
    "TotalSupply": 3000000,
    "PrizeStructure": {
      "50000000": 1,
      "5000000": 3,
      "100000": 50,
      "50000": 100,
      "30000": 550,
      "25000": 2000,
      "11000": 5000,
      "9000": 6000,
      "6000": 8250,
      "5000": 30000,
      "4000": 60000,
      "3000": 60000,
      "2000": 360000,
      "1000": 420000
    }
  },
  {
    "Name": "Kávészünet 500",
    "Price": 500,
    "ReleaseDate": "2020-07-10",
    "EndDate": "2021-08-22",
    "TotalSupply": 3000000,
    "PrizeStructure": {
      "25000000": 1,
      "1000000": 5,
      "100000": 60,
      "50000": 680,
      "20000": 1500,
      "10000": 10000,
      "5000": 21400,
      "2500": 20000,
      "1000": 120000,
      "800": 360000,
      "500": 420000
    }
  },
  {
    "Name": "Kincseskamra",
    "Price": 2000,
    "ReleaseDate": "2020-09-04",
    "EndDate": "2023-02-19",
    "TotalSupply": 3000000,
    "PrizeStructure": {
      "75000000": 1,
      "10000000": 5,
      "1000000": 15,
      "100000": 500,
      "50000": 3000,
      "40000": 5000,
      "30000": 7000,
      "20000": 10500,
      "15000": 14000,
      "10000": 25000,
      "7000": 20000,
      "6000": 40000,
      "5000": 60000,
      "4000": 120000,
      "3000": 240000,
      "2000": 420000
    }
  },
  {
    "Name": "Kiskarácsony 2020",
    "Price": 500,
    "ReleaseDate": "2020-11-06",
    "EndDate": "2021-02-28",
    "TotalSupply": 6000000,
    "PrizeStructure": {
      "25000000": 1,
      "5000000": 5,
      "100000": 100,
      "50000": 2000,
      "25000": 2000,
      "18000": 2500,
      "12000": 6500,
      "8000": 4500,
      "4000": 12000,
      "3000": 11000,
      "2000": 120000,
      "1500": 240000,
      "1000": 480000,
      "500": 840000
    }
  },
  {
    "Name": "Nagykarácsony 2020",
    "Price": 3000,
    "ReleaseDate": "2020-11-06",
    "EndDate": "2021-02-28",
    "TotalSupply": 2500000,
    "PrizeStructure": {
      "100000000": 1,
      "10000000": 30,
      "1000000": 100,
      "100000": 1000,
      "45000": 4000,
      "30000": 4000,
      "21000": 7000,
      "15000": 9000,
      "12000": 14000,
      "9000": 100000,
      "6000": 300000,
      "3000": 400000
    }
  },
  {
    "Name": "Napi Bónusz",
    "Price": 500,
    "ReleaseDate": "2021-01-15",
    "EndDate": "2022-07-24",
    "TotalSupply": 5000000,
    "PrizeStructure": {
      "25000000": 1,
      "1000000": 5,
      "100000": 110,
      "40000": 125,
      "30000": 300,
      "25000": 360,
      "10000": 1100,
      "5000": 20000,
      "3000": 100000,
      "2000": 100000,
      "1000": 600000,
      "500": 700000
    }
  },
  {
    "Name": "Heti Bónusz",
    "Price": 1000,
    "ReleaseDate": "2021-01-15",
    "TotalSupply": 4000000,
    "PrizeStructure": {
      "50000000": 1,
      "1000000": 5,
      "100000": 75,
      "70000": 70,
      "50000": 100,
      "21000": 1500,
      "14000": 1500,
      "10000": 3060,
      "7000": 3500,
      "6000": 40000,
      "5000": 36000,
      "4000": 80000,
      "3000": 80000,
      "2000": 480000,
      "1000": 560000
    }
  },
  {
    "Name": "Havi Bónusz",
    "Price": 2000,
    "ReleaseDate": "2021-01-15",
    "TotalSupply": 3000000,
    "PrizeStructure": {
      "75000000": 1,
      "10000000": 15,
      "3000000": 75,
      "900000": 80,
      "100000": 850,
      "60000": 2800,
      "50000": 1600,
      "35000": 1700,
      "30000": 2000,
      "24000": 4600,
      "14000": 4000,
      "10000": 9310,
      "9000": 8000,
      "8000": 8000,
      "7000": 10000,
      "6000": 50000,
      "5000": 60000,
      "4000": 60000,
      "3000": 300000,
      "2000": 480000
    }
  },
  {
    "Name": "Mega Black Jack",
    "Price": 1000,
    "ReleaseDate": "2021-03-05",
    "TotalSupply": 3000000,
    "PrizeStructure": {
      "50000000": 1,
      "1000000": 5,
      "100000": 50,
      "50000": 80,
      "30000": 400,
      "25000": 1600,
      "12000": 4000,
      "8000": 8750,
      "6000": 11000,
      "5000": 30000,
      "4000": 60000,
      "3000": 60000,
      "2000": 360000,
      "1000": 420000
    }
  },
  {
    "Name": "Pénzkerék",
    "Price": 1000,
    "ReleaseDate": "2021-05-07",
    "EndDate": "2022-11-13",
    "TotalSupply": 4000000,
    "PrizeStructure": {
      "50000000": 1,
      "5000000": 3,
      "100000": 50,
      "50000": 100,
      "30000": 550,
      "25000": 2000,
      "11000": 4000,
      "9000": 6000,
      "6000": 7500,
      "5000": 47100,
      "4000": 80000,
      "3000": 160000,
      "2000": 400000,
      "1000": 560000
    }
  },
  {
    "Name": "Óriás Pénzkerék",
    "Price": 2000,
    "ReleaseDate": "2021-05-07",
    "EndDate": "2023-07-16",
    "TotalSupply": 4000000,
    "PrizeStructure": {
      "75000000": 1,
      "10000000": 8,
      "1000000": 25,
      "120000": 700,
      "100000": 1000,
      "60000": 2500,
      "40000": 5000,
      "30000": 7000,
      "21000": 9000,
      "20000": 10500,
      "15000": 14000,
      "10000": 16050,
      "9000": 18500,
      "7000": 20000,
      "6000": 80000,
      "5000": 80000,
      "4000": 160000,
      "3000": 240000,
      "2000": 640000
    }
  },
  {
    "Name": "Retro borítékos sorsjegy",
    "Price": 500,
    "ReleaseDate": "2021-07-09",
    "EndDate": "2022-05-22",
    "TotalSupply": 5000000,
    "PrizeStructure": {
      "30000000": 1,
      "900000": 5,
      "100000": 25,
      "60000": 50,
      "40000": 50,
      "30000": 200,
      "20000": 1000,
      "15000": 3000,
      "10000": 6000,
      "6000": 7000,
      "5000": 25000,
      "3000": 50000,
      "2000": 100000,
      "1000": 200000,
      "800": 450000,
      "500": 750000
    }
  },
  {
    "Name": "Varázsfőzet",
    "Price": 2000,
    "ReleaseDate": "2021-09-10",
    "EndDate": "2023-04-23",
    "TotalSupply": 3000000,
    "PrizeStructure": {
      "75000000": 2,
      "10000000": 5,
      "1000000": 10,
      "100000": 20,
      "80000": 50,
      "60000": 1400,
      "50000": 2500,
      "30000": 3000,
      "25000": 10000,
      "20000": 17000,
      "10000": 15000,
      "9000": 20000,
      "8000": 20000,
      "6000": 39500,
      "5000": 50000,
      "4000": 105000,
      "3000": 226000,
      "2000": 480000
    }
  },
  {
    "Name": "Kiskarácsony 2021",
    "Price": 500,
    "ReleaseDate": "2021-11-05",
    "EndDate": "2022-03-20",
    "TotalSupply": 5500000,
    "PrizeStructure": {
      "25000000": 1,
      "1000000": 5,
      "100000": 40,
      "50000": 80,
      "40000": 50,
      "30000": 600,
      "20000": 650,
      "15000": 1000,
      "10000": 2150,
      "6000": 3000,
      "3000": 70000,
      "2000": 220000,
      "1000": 330000,
      "800": 440000,
      "500": 660000
    }
  },
  {
    "Name": "Nagykarácsony 2021",
    "Price": 3000,
    "ReleaseDate": "2021-11-05",
    "EndDate": "2022-03-20",
    "TotalSupply": 2400000,
    "PrizeStructure": {
      "100000000": 1,
      "10000000": 10,
      "1000000": 100,
      "100000": 1480,
      "45000": 4200,
      "30000": 7000,
      "20000": 12000,
      "15000": 30000,
      "10000": 33500,
      "6000": 96000,
      "5000": 288000,
      "3000": 384000
    }
  },
  {
    "Name": "Sok szerencsét! 2022",
    "Price": 1000,
    "ReleaseDate": "2021-12-30",
    "EndDate": "2022-09-25",
    "TotalSupply": 3000000,
    "PrizeStructure": {
      "50000000": 1,
      "5000000": 5,
      "100000": 65,
      "50000": 100,
      "30000": 400,
      "25000": 2000,
      "12000": 7000,
      "9000": 4500,
      "6000": 4500,
      "5000": 30000,
      "4000": 60000,
      "3000": 60000,
      "2000": 360000,
      "1000": 420000
    }
  },
  {
    "Name": "Vadvilág 500",
    "Price": 500,
    "ReleaseDate": "2022-02-04",
    "EndDate": "2023-09-17",
    "TotalSupply": 5000000,
    "PrizeStructure": {
      "25000000": 1,
      "1000000": 5,
      "100000": 24,
      "50000": 40,
      "40000": 50,
      "30000": 240,
      "20000": 1520,
      "15000": 1400,
      "10000": 8000,
      "5000": 20000,
      "3000": 100000,
      "2000": 50000,
      "1000": 200000,
      "800": 500000,
      "500": 700000
    }
  },
  {
    "Name": "Vadvilág 1000",
    "Price": 1000,
    "ReleaseDate": "2022-02-04",
    "EndDate": "2023-09-17",
    "TotalSupply": 3000000,
    "PrizeStructure": {
      "50000000": 1,
      "5000000": 5,
      "100000": 20,
      "50000": 40,
      "40000": 50,
      "30000": 270,
      "20000": 600,
      "15000": 1000,
      "10000": 3590,
      "7000": 4000,
      "6000": 5000,
      "5000": 12000,
      "4000": 60000,
      "3000": 120000,
      "2000": 360000,
      "1000": 420000
    }
  },
  {
    "Name": "Vadvilág 2000",
    "Price": 2000,
    "ReleaseDate": "2022-02-04",
    "EndDate": "2024-01-21",
    "TotalSupply": 3000000,
    "PrizeStructure": {
      "75000000": 1,
      "10000000": 14,
      "1000000": 40,
      "100000": 310,
      "50000": 3000,
      "40000": 3700,
      "30000": 4000,
      "20000": 14000,
      "17000": 12000,
      "10000": 14000,
      "7000": 16000,
      "6000": 30000,
      "5000": 60000,
      "4000": 120000,
      "3000": 300000,
      "2000": 420000
    }
  },
  {
    "Name": "Pénzmátrix",
    "Price": 500,
    "ReleaseDate": "2022-03-25",
    "EndDate": "2023-11-12",
    "TotalSupply": 5000000,
    "PrizeStructure": {
      "25000000": 1,
      "1000000": 5,
      "100000": 110,
      "50000": 300,
      "20000": 2000,
      "10000": 3900,
      "5000": 50000,
      "2000": 150000,
      "1500": 100000,
      "1000": 200000,
      "800": 300000,
      "500": 700000
    }
  },
  {
    "Name": "Ökokaland",
    "Price": 1000,
    "ReleaseDate": "2022-05-13",
    "TotalSupply": 3000000,
    "PrizeStructure": {
      "50000000": 1,
      "1000000": 10,
      "100000": 115,
      "45000": 100,
      "30000": 500,
      "25000": 2000,
      "20000": 2000,
      "9000": 3000,
      "6000": 7000,
      "5000": 40000,
      "4000": 60000,
      "3000": 60000,
      "2000": 360000,
      "1000": 420000
    }
  },
  {
    "Name": "Ökokaland Extra",
    "Price": 2000,
    "ReleaseDate": "2022-05-13",
    "TotalSupply": 3000000,
    "PrizeStructure": {
      "75000000": 1,
      "10000000": 5,
      "1000000": 25,
      "100000": 600,
      "50000": 3100,
      "40000": 5000,
      "30000": 7000,
      "20000": 11000,
      "15000": 15400,
      "10000": 18000,
      "7000": 22000,
      "6000": 20000,
      "5000": 60000,
      "4000": 120000,
      "3000": 240000,
      "2000": 480000
    }
  },
  {
    "Name": "Nyomkövető",
    "Price": 500,
    "ReleaseDate": "2022-07-08",
    "TotalSupply": 5000000,
    "PrizeStructure": {
      "25000000": 1,
      "5000000": 5,
      "100000": 160,
      "50000": 160,
      "20000": 200,
      "16000": 2000,
      "10000": 2000,
      "6000": 7500,
      "5000": 50000,
      "2000": 100000,
      "1300": 100000,
      "1000": 200000,
      "800": 400000,
      "500": 700000
    }
  },
  {
    "Name": "Kincsvadász",
    "Price": 2000,
    "ReleaseDate": "2022-09-09",
    "TotalSupply": 4000000,
    "PrizeStructure": {
      "75000000": 2,
      "5000000": 10,
      "1000000": 50,
      "100000": 200,
      "50000": 1500,
      "30000": 6000,
      "22000": 10000,
      "20000": 19500,
      "15000": 22000,
      "10000": 23000,
      "9000": 25000,
      "8000": 30000,
      "6000": 40000,
      "5000": 80000,
      "4000": 160000,
      "3000": 320000,
      "2000": 560000
    }
  },
  {
    "Name": "Kiskarácsony 2022",
    "Price": 500,
    "ReleaseDate": "2022-11-04",
    "EndDate": "2023-03-19",
    "TotalSupply": 5500000,
    "PrizeStructure": {
      "25000000": 1,
      "1000000": 5,
      "100000": 65,
      "50000": 40,
      "40000": 50,
      "30000": 450,
      "20000": 550,
      "15000": 860,
      "12000": 2300,
      "5000": 35000,
      "3000": 55000,
      "1500": 220000,
      "1000": 330000,
      "800": 440000,
      "500": 660000
    }
  },
  {
    "Name": "Nagykarácsony 2022",
    "Price": 3000,
    "ReleaseDate": "2022-11-04",
    "EndDate": "2023-03-19",
    "TotalSupply": 2400000,
    "PrizeStructure": {
      "100000000": 1,
      "10000000": 30,
      "1000000": 100,
      "100000": 280,
      "50000": 1590,
      "30000": 1400,
      "27000": 1000,
      "24000": 4000,
      "21000": 6000,
      "15000": 14000,
      "12000": 15500,
      "9000": 85500,
      "6000": 192000,
      "5000": 192000,
      "3000": 288000
    }
  },
  {
    "Name": "Sok szerencsét! 2023",
    "Price": 1000,
    "ReleaseDate": "2022-12-30",
    "EndDate": "2023-09-17",
    "TotalSupply": 5000000,
    "PrizeStructure": {
      "50000000": 1,
      "5000000": 5,
      "100000": 120,
      "50000": 200,
      "30000": 300,
      "25000": 1000,
      "12000": 6000,
      "9000": 13000,
      "6000": 20000,
      "5000": 62000,
      "4000": 100000,
      "3000": 200000,
      "2000": 400000,
      "1000": 800000
    }
  },
  {
    "Name": "NEON 500",
    "Price": 500,
    "ReleaseDate": "2023-02-03",
    "TotalSupply": 5000000,
    "PrizeStructure": {
      "25000000": 1,
      "1000000": 3,
      "100000": 24,
      "50000": 60,
      "30000": 170,
      "20000": 1000,
      "15000": 1100,
      "10000": 2100,
      "6000": 6500,
      "5000": 8000,
      "3000": 100000,
      "2000": 100000,
      "1000": 200000,
      "800": 500000,
      "500": 700000
    }
  },
  {
    "Name": "NEON 1000",
    "Price": 1000,
    "ReleaseDate": "2023-02-03",
    "TotalSupply": 4000000,
    "PrizeStructure": {
      "50000000": 1,
      "1000000": 6,
      "150000": 60,
      "100000": 80,
      "50000": 120,
      "30000": 350,
      "20000": 1500,
      "10000": 3000,
      "9000": 3500,
      "8000": 4000,
      "7000": 6000,
      "6000": 10000,
      "5000": 25000,
      "4000": 80000,
      "3000": 160000,
      "2000": 400000,
      "1000": 640000
    }
  },
  {
    "Name": "NEON 2000",
    "Price": 2000,
    "ReleaseDate": "2023-02-03",
    "TotalSupply": 2500000,
    "PrizeStructure": {
      "75000000": 1,
      "10000000": 5,
      "1000000": 10,
      "500000": 200,
      "100000": 200,
      "60000": 800,
      "50000": 1710,
      "40000": 3000,
      "30000": 4100,
      "25000": 4500,
      "20000": 5000,
      "15000": 6000,
      "10000": 10000,
      "9000": 12000,
      "6000": 18000,
      "5000": 50000,
      "4000": 100000,
      "3000": 250000,
      "2000": 400000
    }
  },
  {
    "Name": "Atlantisz",
    "Price": 2000,
    "ReleaseDate": "2023-03-24",
    "TotalSupply": 3000000,
    "PrizeStructure": {
      "75000000": 2,
      "10000000": 5,
      "1000000": 10,
      "100000": 20,
      "80000": 50,
      "60000": 1400,
      "50000": 2500,
      "30000": 3000,
      "25000": 10000,
      "20000": 17000,
      "10000": 15000,
      "9000": 20000,
      "8000": 20000,
      "6000": 39500,
      "5000": 50000,
      "4000": 105000,
      "3000": 226000,
      "2000": 480000
    }
  },
  {
    "Name": "Kis Meglepetés",
    "Price": 500,
    "ReleaseDate": "2023-05-12",
    "TotalSupply": 5000000,
    "PrizeStructure": {
      "25000000": 1,
      "1000000": 3,
      "100000": 14,
      "50000": 60,
      "30000": 170,
      "20000": 900,
      "14000": 1300,
      "10000": 2230,
      "6000": 6500,
      "5000": 8000,
      "3000": 100000,
      "2000": 100000,
      "1000": 200000,
      "800": 500000,
      "500": 700000
    }
  },
  {
    "Name": "Nagy Meglepetés",
    "Price": 1000,
    "ReleaseDate": "2023-05-12",
    "TotalSupply": 4000000,
    "PrizeStructure": {
      "50000000": 1,
      "1000000": 5,
      "100000": 80,
      "50000": 120,
      "30000": 350,
      "15000": 4000,
      "9000": 6500,
      "8000": 4000,
      "6000": 10000,
      "5000": 30000,
      "4000": 80000,
      "3000": 160000,
      "2000": 400000,
      "1000": 640000
    }
  },
  {
    "Name": "Óriási Meglepetés",
    "Price": 2000,
    "ReleaseDate": "2023-05-12",
    "TotalSupply": 2500000,
    "PrizeStructure": {
      "75000000": 1,
      "10000000": 5,
      "1000000": 10,
      "500000": 200,
      "100000": 200,
      "60000": 800,
      "40000": 4500,
      "24000": 6000,
      "20000": 5000,
      "16000": 6000,
      "10000": 22000,
      "8000": 12000,
      "6000": 18500,
      "5000": 50000,
      "4000": 100000,
      "3000": 250000,
      "2000": 400000
    }
  },
  {
    "Name": "Puzzle",
    "Price": 1000,
    "ReleaseDate": "2023-07-07",
    "TotalSupply": 5000000,
    "PrizeStructure": {
      "50000000": 1,
      "1000000": 5,
      "100000": 50,
      "50000": 100,
      "25000": 500,
      "20000": 500,
      "12000": 6000,
      "10000": 2850,
      "8000": 8000,
      "7000": 10000,
      "6000": 38000,
      "5000": 100000,
      "2000": 800000,
      "1000": 700000
    }
  },
  {
    "Name": "Milliomos Klub",
    "Price": 2500,
    "ReleaseDate": "2023-09-01",
    "TotalSupply": 3000000,
    "PrizeStructure": {
      "85000000": 2,
      "5000000": 45,
      "1000000": 265,
      "100000": 600,
      "50000": 5000,
      "30000": 12000,
      "25000": 11000,
      "17500": 4000,
      "15000": 4000,
      "10000": 20000,
      "7500": 80000,
      "5000": 60000,
      "3000": 480000,
      "2500": 360000
    }
  },
  {
    "Name": "Kiskarácsony 2023",
    "Price": 1000,
    "ReleaseDate": "2023-10-27",
    "TotalSupply": 6000000,
    "PrizeStructure": {
      "50000000": 1,
      "1000000": 6,
      "100000": 45,
      "50000": 100,
      "25000": 650,
      "20000": 670,
      "15000": 870,
      "10000": 1600,
      "8000": 2600,
      "7000": 5000,
      "5000": 120000,
      "4000": 120000,
      "3000": 240000,
      "2000": 600000,
      "1000": 840000
    }
  },
  {
    "Name": "Nagykarácsony 2023",
    "Price": 3500,
    "ReleaseDate": "2023-10-27",
    "TotalSupply": 3200000,
    "PrizeStructure": {
      "125000000": 1,
      "75000000": 1,
      "1000000": 100,
      "100000": 415,
      "50000": 2100,
      "45000": 2500,
      "35000": 3000,
      "20000": 14000,
      "15000": 64000,
      "14000": 64000,
      "10000": 64000,
      "7000": 128000,
      "6000": 128000,
      "5000": 256000,
      "3500": 384000
    }
  },
  {
    "Name": "Sok szerencsét! 2024",
    "Price": 1000,
    "ReleaseDate": "2023-12-27",
    "TotalSupply": 6000000,
    "PrizeStructure": {
      "50000000": 1,
      "1000000": 5,
      "100000": 55,
      "50000": 100,
      "30000": 300,
      "25000": 900,
      "12000": 6000,
      "9000": 10000,
      "6000": 16000,
      "5000": 25000,
      "4000": 120000,
      "3000": 240000,
      "2000": 720000,
      "1000": 840000
    }
  },
  {
    "Name": "Kis Kerék",
    "Price": 500,
    "ReleaseDate": "2024-02-02",
    "TotalSupply": 6000000,
    "PrizeStructure": {
      "25000000": 1,
      "1000000": 5,
      "100000": 30,
      "50000": 100,
      "20000": 500,
      "10000": 1000,
      "6000": 2000,
      "5000": 4000,
      "2000": 240000,
      "1000": 900000,
      "500": 840000
    }
  },
  {
    "Name": "Nagy Kerék",
    "Price": 1000,
    "ReleaseDate": "2024-02-02",
    "TotalSupply": 5500000,
    "PrizeStructure": {
      "50000000": 1,
      "1000000": 10,
      "100000": 100,
      "50000": 200,
      "20000": 2250,
      "10000": 5000,
      "8000": 10000,
      "5000": 70000,
      "4000": 110000,
      "2000": 880000,
      "1000": 770000
    }
  },
  {
    "Name": "Óriási Kerék",
    "Price": 2000,
    "ReleaseDate": "2024-02-02",
    "TotalSupply": 4000000,
    "PrizeStructure": {
      "100000000": 1,
      "10000000": 5,
      "1000000": 50,
      "100000": 200,
      "40000": 6500,
      "20000": 16000,
      "10000": 40000,
      "4000": 720000,
      "2000": 600000
    }
  },
  {
    "Name": "Nyereményözön",
    "Price": 1000,
    "ReleaseDate": "2024-03-08",
    "TotalSupply": 5000000,
    "PrizeStructure": {
      "50000": 4000,
      "10000": 40000,
      "5000": 100000,
      "3000": 150000,
      "2000": 500000,
      "1000": 700000
    }
  },
  {
    "Name": "Kaszinó 171",
    "Price": 2000,
    "ReleaseDate": "2024-03-14",
    "TotalSupply": 3000000,
    "PrizeStructure": {
      "75000000": 1,
      "10000000": 3,
      "1000000": 21,
      "100000": 270,
      "50000": 2700,
      "40000": 4500,
      "30000": 6000,
      "20000": 10200,
      "15000": 14000,
      "10000": 16000,
      "7000": 20000,
      "6000": 23000,
      "5000": 60000,
      "4000": 120000,
      "3000": 240000,
      "2000": 480000
    }
  },
  {
    "Name": "Buksza 170",
    "Price": 1000,
    "ReleaseDate": "2024-03-27",
    "TotalSupply": 5000000,
    "PrizeStructure": {
      "50000000": 1,
      "5000000": 3,
      "100000": 50,
      "50000": 150,
      "27000": 600,
      "22000": 1900,
      "11000": 4500,
      "10000": 16000,
      "9000": 10000,
      "8000": 10000,
      "6000": 10000,
      "5000": 55000,
      "4000": 100000,
      "3000": 100000,
      "2000": 500000,
      "1000": 700000
    }
  },
  {
    "Name": "Ajándék",
    "Price": 2000,
    "ReleaseDate": "2024-04-12",
    "TotalSupply": 8000000,
    "PrizeStructure": {
      "100000000": 2,
      "10000000": 5,
      "1000000": 45,
      "100000": 200,
      "50000": 400,
      "10000": 2500,
      "7500": 160000,
      "5000": 1200000,
      "2500": 1200000
    }
  }
]
